mmrotate/__init__.py
mmrotate/version.py
mmrotate/.mim/model-index.yml
mmrotate/.mim/configs/_base_/default_runtime.py
mmrotate/.mim/configs/_base_/datasets/dotav1.py
mmrotate/.mim/configs/_base_/datasets/hrsc.py
mmrotate/.mim/configs/_base_/datasets/hrsid.py
mmrotate/.mim/configs/_base_/datasets/ssdd.py
mmrotate/.mim/configs/_base_/schedules/schedule_1x.py
mmrotate/.mim/configs/_base_/schedules/schedule_3x.py
mmrotate/.mim/configs/_base_/schedules/schedule_40e.py
mmrotate/.mim/configs/_base_/schedules/schedule_6x.py
mmrotate/.mim/configs/cfa/cfa_r50_fpn_1x_dota_le135.py
mmrotate/.mim/configs/cfa/cfa_r50_fpn_1x_dota_oc.py
mmrotate/.mim/configs/cfa/cfa_r50_fpn_40e_dota_oc.py
mmrotate/.mim/configs/cfa/metafile.yml
mmrotate/.mim/configs/convnext/metafile.yml
mmrotate/.mim/configs/convnext/rotated_retinanet_obb_kld_stable_convnext_adamw_fpn_1x_dota_le90.py
mmrotate/.mim/configs/csl/metafile.yml
mmrotate/.mim/configs/csl/rotated_retinanet_obb_csl_gaussian_r50_fpn_fp16_1x_dota_le90.py
mmrotate/.mim/configs/g_reppoints/g_reppoints_r50_fpn_1x_dota_le135.py
mmrotate/.mim/configs/g_reppoints/metafile.yml
mmrotate/.mim/configs/gliding_vertex/gliding_vertex_r50_fpn_1x_dota_le90.py
mmrotate/.mim/configs/gliding_vertex/metafile.yml
mmrotate/.mim/configs/gwd/metafile.yml
mmrotate/.mim/configs/gwd/rotated_retinanet_hbb_gwd_r50_fpn_1x_dota_oc.py
mmrotate/.mim/configs/gwd/rotated_retinanet_obb_gwd_r50_fpn_1x_dota_le135.py
mmrotate/.mim/configs/gwd/rotated_retinanet_obb_gwd_r50_fpn_1x_dota_le90.py
mmrotate/.mim/configs/kfiou/metafile.yml
mmrotate/.mim/configs/kfiou/r3det_kfiou_ln_r50_fpn_1x_dota_oc.py
mmrotate/.mim/configs/kfiou/r3det_kfiou_ln_swin_tiny_adamw_fpn_1x_dota_ms_rr_oc.py
mmrotate/.mim/configs/kfiou/r3det_kfiou_ln_swin_tiny_adamw_fpn_2x_dota_ms_rr_oc.py
mmrotate/.mim/configs/kfiou/r3det_refine_kfiou_ln_r50_fpn_1x_dota_oc.py
mmrotate/.mim/configs/kfiou/r3det_tiny_kfiou_ln_r50_fpn_1x_dota_oc.py
mmrotate/.mim/configs/kfiou/roi_trans_kfiou_ln_r50_fpn_1x_dota_le90.py
mmrotate-0.3.4.dist-info/LICENSE
mmrotate-0.3.4.dist-info/METADATA
mmrotate-0.3.4.dist-info/WHEEL
mmrotate-0.3.4.dist-info/top_level.txt
mmrotate-0.3.4.dist-info/RECORD
